backdoormbti/__init__.py
backdoormbti/cli_atk.py
backdoormbti/cli_def.py
backdoormbti/attacks/__init__.py
backdoormbti/attacks/base.py
backdoormbti/attacks/audio/__init__.py
backdoormbti/attacks/audio/baasv.py
backdoormbti/attacks/audio/badnet.py
backdoormbti/attacks/audio/base.py
backdoormbti/attacks/audio/blend.py
backdoormbti/attacks/audio/daba.py
backdoormbti/attacks/audio/gis.py
backdoormbti/attacks/audio/ultrasonic.py
backdoormbti/attacks/image/DynaTrigger.py
backdoormbti/attacks/image/__init__.py
backdoormbti/attacks/image/adaptive_blend.py
backdoormbti/attacks/image/badnet.py
backdoormbti/attacks/image/base.py
backdoormbti/attacks/image/blend.py
backdoormbti/attacks/image/blind.py
backdoormbti/attacks/image/bpp.py
backdoormbti/attacks/image/embtrojan.py
backdoormbti/attacks/image/hpt.py
backdoormbti/attacks/image/iad.py
backdoormbti/attacks/image/imc.py
backdoormbti/attacks/image/labelconsistent.py
backdoormbti/attacks/image/lowfreq.py
backdoormbti/attacks/image/marksman.py
backdoormbti/attacks/image/pnoiseattack.py
backdoormbti/attacks/image/refool.py
backdoormbti/attacks/image/sbat.py
backdoormbti/attacks/image/sig.py
backdoormbti/attacks/image/ssba.py
backdoormbti/attacks/image/trojan.py
backdoormbti/attacks/image/ubw.py
backdoormbti/attacks/image/wanet.py
backdoormbti/attacks/image/LIRA/lira_backdoor_injection.py
backdoormbti/attacks/image/LIRA/lira_trigger_generation.py
backdoormbti/attacks/image/LIRA/attack_models/unet.py
backdoormbti/attacks/image/LIRA/utils/__init__.py
backdoormbti/attacks/image/LIRA/utils/dataloader.py
backdoormbti/attacks/text/__init__.py
backdoormbti/attacks/text/addsent.py
backdoormbti/attacks/text/badnet.py
backdoormbti/attacks/text/base.py
backdoormbti/attacks/text/bite.py
backdoormbti/attacks/text/lwp.py
backdoormbti/attacks/text/stylebkd.py
backdoormbti/attacks/text/synbkd.py
backdoormbti/attacks/video/__init__.py
backdoormbti/attacks/video/badnet.py
backdoormbti/attacks/video/base.py
backdoormbti/attacks/video/blend.py
backdoormbti-0.2.2.dist-info/METADATA
backdoormbti-0.2.2.dist-info/WHEEL
backdoormbti-0.2.2.dist-info/entry_points.txt
backdoormbti-0.2.2.dist-info/top_level.txt
backdoormbti-0.2.2.dist-info/RECORD
