Metadata-Version: 2.1
Name: backdoormbti
Version: 0.2.2
Summary: An open-source framework for backdoor learning and defense in multimodal contexts
Home-page: https://github.com/SJTUHaiyangYu/BackdoorMBTI
Author: anonymous
Author-email: anonymous@gmail.com
Classifier: Programming Language :: Python :: 3.10
Classifier: License :: OSI Approved :: MIT License
Classifier: Operating System :: POSIX :: Linux
Requires-Python: >=3.10
Requires-Dist: aiohttp==3.8.4
Requires-Dist: aiosignal==1.3.1
Requires-Dist: anyio==3.6.2
Requires-Dist: appdirs==1.4.4
Requires-Dist: arrow==1.2.3
Requires-Dist: asttokens==2.2.1
Requires-Dist: async-timeout==4.0.2
Requires-Dist: attrs==23.1.0
Requires-Dist: audioread==3.0.0
Requires-Dist: av==10.0.0
Requires-Dist: backcall==0.2.0
Requires-Dist: backports.functools-lru-cache==1.6.4
Requires-Dist: bchlib==0.14.0
Requires-Dist: beautifulsoup4==4.12.2
Requires-Dist: blessed==1.20.0
Requires-Dist: certifi==2022.12.7
Requires-Dist: cffi==1.15.1
Requires-Dist: charset-normalizer==3.1.0
Requires-Dist: click==8.1.3
Requires-Dist: cmake==3.26.3
Requires-Dist: comm==0.1.3
Requires-Dist: contourpy==1.1.0
Requires-Dist: croniter==1.3.14
Requires-Dist: cycler==0.11.0
Requires-Dist: Cython==0.29.36
Requires-Dist: datasets==2.14.2
Requires-Dist: dateutils==0.6.12
Requires-Dist: debugpy==1.6.7
Requires-Dist: decorator==5.1.1
Requires-Dist: deepdiff==6.3.0
Requires-Dist: dill==0.3.7
Requires-Dist: evaluate==0.4.0
Requires-Dist: exceptiongroup==1.1.1
Requires-Dist: executing==1.2.0
Requires-Dist: fastapi==0.88.0
Requires-Dist: filelock==3.12.0
Requires-Dist: fonttools==4.42.0
Requires-Dist: frozenlist==1.3.3
Requires-Dist: fsspec==2023.4.0
Requires-Dist: gdown==4.7.1
Requires-Dist: h11==0.14.0
Requires-Dist: hdbscan==0.8.33
Requires-Dist: huggingface-hub==0.15.1
Requires-Dist: idna==3.4
Requires-Dist: imageio==2.31.1
Requires-Dist: iniconfig==2.0.0
Requires-Dist: inquirer==3.1.3
Requires-Dist: ipykernel==6.23.3
Requires-Dist: ipython==8.14.0
Requires-Dist: isort==5.12.0
Requires-Dist: itsdangerous==2.1.2
Requires-Dist: jedi==0.18.2
Requires-Dist: Jinja2==3.1.2
Requires-Dist: joblib==1.2.0
Requires-Dist: jsonlines==3.1.0
Requires-Dist: jupyter-client==8.3.0
Requires-Dist: jupyter-core==5.3.1
Requires-Dist: kiwisolver==1.4.4
Requires-Dist: language-tool-python==2.7.1
Requires-Dist: lazy-loader==0.3
Requires-Dist: librosa==0.10.0.post2
Requires-Dist: lightning==2.1.2
Requires-Dist: lightning-cloud==0.5.33
Requires-Dist: lightning-utilities==0.8.0
Requires-Dist: lit==16.0.1
Requires-Dist: llvmlite==0.40.1
Requires-Dist: markdown-it-py==2.2.0
Requires-Dist: MarkupSafe==2.1.2
Requires-Dist: matplotlib==3.7.2
Requires-Dist: matplotlib-inline==0.1.6
Requires-Dist: mdurl==0.1.2
Requires-Dist: mpmath==1.3.0
Requires-Dist: msgpack==1.0.5
Requires-Dist: multidict==6.0.4
Requires-Dist: multiprocess==0.70.15
Requires-Dist: mypy-extensions==0.4.3
Requires-Dist: nest-asyncio==1.5.6
Requires-Dist: noise==1.2.2
Requires-Dist: networkx==3.1
Requires-Dist: nlpaug==1.1.11
Requires-Dist: nltk==3.8.1
Requires-Dist: numba==0.57.1
Requires-Dist: numpy==1.23.5
Requires-Dist: nvidia-cublas-cu11==11.10.3.66
Requires-Dist: nvidia-cuda-cupti-cu11==11.7.101
Requires-Dist: nvidia-cuda-nvrtc-cu11==11.7.99
Requires-Dist: nvidia-cuda-runtime-cu11==11.7.99
Requires-Dist: nvidia-cudnn-cu11==8.5.0.96
Requires-Dist: nvidia-cufft-cu11==10.9.0.58
Requires-Dist: nvidia-curand-cu11==10.2.10.91
Requires-Dist: nvidia-cusolver-cu11==11.4.0.1
Requires-Dist: nvidia-cusparse-cu11==11.7.4.91
Requires-Dist: nvidia-nccl-cu11==2.14.3
Requires-Dist: nvidia-nvtx-cu11==11.7.91
Requires-Dist: OpenAttack==2.1.1
Requires-Dist: opencv-python==4.8.1.78
Requires-Dist: ordered-set==4.1.0
Requires-Dist: packaging==23.1
Requires-Dist: pandas==2.0.3
Requires-Dist: parso==0.8.3
Requires-Dist: pathspec==0.10.3
Requires-Dist: pedalboard==0.8.1
Requires-Dist: pexpect==4.8.0
Requires-Dist: pickleshare==0.7.5
Requires-Dist: Pillow==9.5.0
Requires-Dist: pip==23.0.1
Requires-Dist: platformdirs==2.5.2
Requires-Dist: pluggy==1.0.0
Requires-Dist: pooch==1.6.0
Requires-Dist: portalocker==2.7.0
Requires-Dist: prompt-toolkit==3.0.38
Requires-Dist: protobuf==4.25.1
Requires-Dist: psutil==5.9.5
Requires-Dist: ptyprocess==0.7.0
Requires-Dist: pure-eval==0.2.2
Requires-Dist: pyarrow==12.0.1
Requires-Dist: pycparser==2.21
Requires-Dist: pydantic==1.10.7
Requires-Dist: pydub==0.25.1
Requires-Dist: Pygments==2.15.1
Requires-Dist: PyJWT==2.6.0
Requires-Dist: pynndescent==0.5.10
Requires-Dist: pyparsing==3.0.9
Requires-Dist: PySocks==1.7.1
Requires-Dist: pytest==7.3.1
Requires-Dist: python-dateutil==2.8.2
Requires-Dist: python-editor==1.0.4
Requires-Dist: python-multipart==0.0.6
Requires-Dist: pytorch-lightning==2.0.1.post0
Requires-Dist: pytz==2023.3
Requires-Dist: PyYAML==6.0
Requires-Dist: pyzmq==25.1.0
Requires-Dist: readchar==4.0.5
Requires-Dist: regex==2023.6.3
Requires-Dist: requests==2.28.2
Requires-Dist: resampy==0.4.2
Requires-Dist: responses==0.18.0
Requires-Dist: rich==13.3.4
Requires-Dist: safetensors==0.3.1
Requires-Dist: scikit-learn==1.2.2
Requires-Dist: scipy==1.10.1
Requires-Dist: sentence-transformers==2.2.2
Requires-Dist: sentencepiece==0.1.99
Requires-Dist: setuptools==66.0.0
Requires-Dist: six==1.16.0
Requires-Dist: sniffio==1.3.0
Requires-Dist: soundfile==0.12.1
Requires-Dist: soupsieve==2.4.1
Requires-Dist: soxr==0.3.5
Requires-Dist: stack-data==0.6.2
Requires-Dist: starlette==0.22.0
Requires-Dist: starsessions==1.3.0
Requires-Dist: strsimpy==0.2.1
Requires-Dist: sympy==1.11.1
Requires-Dist: tensorboardX==2.6.2.2
Requires-Dist: threadpoolctl==3.1.0
Requires-Dist: tokenizers==0.13.3
Requires-Dist: tomli==2.0.1
Requires-Dist: torch==2.0.0
Requires-Dist: torchaudio==2.0.1
Requires-Dist: torchdata==0.6.0
Requires-Dist: torchmetrics==0.11.4
Requires-Dist: torchtext==0.15.1
Requires-Dist: torchvision==0.15.1
Requires-Dist: tornado==6.3.2
Requires-Dist: tqdm==4.65.0
Requires-Dist: traitlets==5.9.0
Requires-Dist: transformers==4.30.2
Requires-Dist: triton==2.0.0
Requires-Dist: typing-extensions==4.5.0
Requires-Dist: tzdata==2023.3
Requires-Dist: umap-learn==0.5.3
Requires-Dist: urllib3==1.26.15
Requires-Dist: uvicorn==0.21.1
Requires-Dist: wcwidth==0.2.6
Requires-Dist: websocket-client==1.5.1
Requires-Dist: websockets==11.0.2
Requires-Dist: wget==3.2
Requires-Dist: wheel==0.38.4
Requires-Dist: xxhash==3.3.0
Requires-Dist: yarl==1.9.1
